pysolo/__init__.py
pysolo/boundary.py
pysolo/enums.py
pysolo/c_wrapper/DataPair.py
pysolo/c_wrapper/__init__.py
pysolo/c_wrapper/conversions.py
pysolo/c_wrapper/function_alias.py
pysolo/c_wrapper/masked_op.py
pysolo/c_wrapper/run_solo.py
pysolo/libs/libSolo_18.04.so
pysolo/libs/libSolo_20.04.so
pysolo/libs/solo.dll
pysolo/solo_functions/__init__.py
pysolo/solo_functions/solo_despeckle.py
pysolo/solo_functions/solo_fix_vortex_vels.py
pysolo/solo_functions/solo_flag_freckles.py
pysolo/solo_functions/solo_flag_glitches.py
pysolo/solo_functions/solo_forced_unfolding.py
pysolo/solo_functions/solo_merge_fields.py
pysolo/solo_functions/solo_radial_shear.py
pysolo/solo_functions/solo_rain_rate.py
pysolo/solo_functions/solo_remove_ac_motion.py
pysolo/solo_functions/solo_remove_storm_motion.py
pysolo/solo_functions/solo_ring_zap.py
pysolo/solo_functions/solo_threshold.py
pysolo/solo_functions/solo_unfold_first_good_gate.py
pysolo/solo_functions/solo_unfold_local_wind.py
pysolo/solo_functions/flags/__init__.py
pysolo/solo_functions/flags/solo_assert_bad_flags.py
pysolo/solo_functions/flags/solo_assign_value.py
pysolo/solo_functions/flags/solo_bad_flags_logic.py
pysolo/solo_functions/flags/solo_clear_bad_flags.py
pysolo/solo_functions/flags/solo_copy_bad_flags.py
pysolo/solo_functions/flags/solo_flagged_add.py
pysolo/solo_functions/flags/solo_set_bad_flags.py
pysolo-1.0.11.dist-info/LICENSE
pysolo-1.0.11.dist-info/METADATA
pysolo-1.0.11.dist-info/WHEEL
pysolo-1.0.11.dist-info/top_level.txt
pysolo-1.0.11.dist-info/RECORD
