Metadata-Version: 2.1
Name: pysolo
Version: 1.0.11
Summary: Python interface for Solo II
Home-page: https://github.com/NCAR/lrose-solo-python
Author: Ammar Siddiqi
Author-email: siddiqi91899@gmail.com
Project-URL: Bug Tracker, https://github.com/NCAR/lrose-solo-python/issues
Classifier: Programming Language :: Python :: 3
Classifier: License :: OSI Approved :: MIT License
Classifier: Operating System :: OS Independent
Requires-Python: >=3.6
License-File: LICENSE
Requires-Dist: numpy
Requires-Dist: arm-pyart
